Workbook

Sheet ARRENDAMIENTO
A1: No. de Pago | B1: Saldo Capital | C1: Tasa Interés | D1: Pago Intereses | E1: Pago Capital | F1: Subtotal | G1: I.V.A. | H1: Pago Total
A2: 1 | B2: 1139809.9 | C2: 0.24 | D2: =(B2*C2)/12 -> 22796.199 | E2: =F2-D2 -> 18256.181 | F2: 41052.38 | G2: =F2*0.16 -> 6568.3808 | H2: 47620.77
A3: 2 | B3: =B2-E2 -> 1121553.7 | C3: 0.24 | D3: =(B3*C3)/12 -> 22431.075 | E3: =F3-D3 -> 18621.305 | F3: 41052.38 | G3: =F3*0.16 -> 6568.3808 | H3: 47620.77
A4: 3 | B4: =B3-E3 -> 1102932.4 | C4: 0.24 | D4: =(B4*C4)/12 -> 22058.649 | E4: =F4-D4 -> 18993.731 | F4: 41052.38 | G4: =F4*0.16 -> 6568.3808 | H4: 47620.77
A5: 4 | B5: =B4-E4 -> 1083938.7 | C5: 0.24 | D5: =(B5*C5)/12 -> 21678.774 | E5: =F5-D5 -> 19373.606 | F5: 41052.38 | G5: =F5*0.16 -> 6568.3808 | H5: 47620.77
A6: 5 | B6: =B5-E5 -> 1064565.1 | C6: 0.24 | D6: =(B6*C6)/12 -> 21291.302 | E6: =F6-D6 -> 19761.078 | F6: 41052.38 | G6: =F6*0.16 -> 6568.3808 | H6: 47620.77
A7: 6 | B7: =B6-E6 -> 1044804 | C7: 0.24 | D7: =(B7*C7)/12 -> 20896.081 | E7: =F7-D7 -> 20156.299 | F7: 41052.38 | G7: =F7*0.16 -> 6568.3808 | H7: 47620.77
A8: 7 | B8: =B7-E7 -> 1024647.7 | C8: 0.24 | D8: =(B8*C8)/12 -> 20492.955 | E8: =F8-D8 -> 20559.425 | F8: 41052.38 | G8: =F8*0.16 -> 6568.3808 | H8: 47620.77
A9: 8 | B9: =B8-E8 -> 1004088.3 | C9: 0.24 | D9: =(B9*C9)/12 -> 20081.766 | E9: =F9-D9 -> 20970.614 | F9: 41052.38 | G9: =F9*0.16 -> 6568.3808 | H9: 47620.77
A10: 9 | B10: =B9-E9 -> 983117.69 | C10: 0.24 | D10: =(B10*C10)/12 -> 19662.354 | E10: =F10-D10 -> 21390.026 | F10: 41052.38 | G10: =F10*0.16 -> 6568.3808 | H10: 47620.77
A11: 10 | B11: =B10-E10 -> 961727.66 | C11: 0.24 | D11: =(B11*C11)/12 -> 19234.553 | E11: =F11-D11 -> 21817.827 | F11: 41052.38 | G11: =F11*0.16 -> 6568.3808 | H11: 47620.77
A12: 11 | B12: =B11-E11 -> 939909.84 | C12: 0.24 | D12: =(B12*C12)/12 -> 18798.197 | E12: =F12-D12 -> 22254.183 | F12: 41052.38 | G12: =F12*0.16 -> 6568.3808 | H12: 47620.77
A13: 12 | B13: =B12-E12 -> 917655.65 | C13: 0.24 | D13: =(B13*C13)/12 -> 18353.113 | E13: =F13-D13 -> 22699.267 | F13: 41052.38 | G13: =F13*0.16 -> 6568.3808 | H13: 47620.77
A14: 13 | B14: =B13-E13 -> 894956.39 | C14: 0.24 | D14: =(B14*C14)/12 -> 17899.128 | E14: =F14-D14 -> 23153.252 | F14: 41052.38 | G14: =F14*0.16 -> 6568.3808 | H14: 47620.77
... A25: 24 | B25: =B24-E24 -> 613211.05 | C25: 0.24 | D25: =(B25*C25)/12 -> 12264.221 | E25: =F25-D25 -> 28788.159 | F25: 41052.38 | G25: =F25*0.16 -> 6568.3808 | H25: 47620.77

Sheet SEGURO
A1: No. de Pago | B1: Saldo Capital | C1: Tasa Interés | D1: Pago Intereses | E1: IVA | F1: Pago Capital | G1: PAGO MENSUAL
A2: 1 | B2: 20000 | C2: 0.24 | D2: =(B2*C2)/12 -> 400 | E2: =+PLACAS!E2+'GASTOS DE ARRENDAMIENTO'!E2 -> 45.92 | F2: =G2-D2-E2 -> 1482.6345 | G2: =PMT((C2*1.16/12),12,-B2,0,0) -> 1928.5545
A3: 2 | B3: =B2-F2 -> 18517.365 | C3: 0.24 | D3: =(B3*C3)/12 -> 370.34731 | E3: =D3*0.16 -> 59.25557 | F3: =G3-D3-E3 -> 1498.9516 | G3: =G2 -> 1928.5545
A4: 3 | B4: =B3-F3 -> 17018.414 | C4: 0.24 | D4: =(B4*C4)/12 -> 340.36828 | E4: =D4*0.16 -> 54.458924 | F4: =G4-D4-E4 -> 1533.7273 | G4: =G3 -> 1928.5545
A5: 4 | B5: =B4-F4 -> 15484.687 | C5: 0.24 | D5: =(B5*C5)/12 -> 309.69373 | E5: =D5*0.16 -> 49.550997 | F5: =G5-D5-E5 -> 1569.3098 | G5: =G4 -> 1928.5545
A6: 5 | B6: =B5-F5 -> 13915.377 | C6: 0.24 | D6: =(B6*C6)/12 -> 278.30753 | E6: =D6*0.16 -> 44.529206 | F6: =G6-D6-E6 -> 1605.7178 | G6: =G5 -> 1928.5545
A7: 6 | B7: =B6-F6 -> 12309.659 | C7: 0.24 | D7: =(B7*C7)/12 -> 246.19318 | E7: =D7*0.16 -> 39.390909 | F7: =G7-D7-E7 -> 1642.9704 | G7: =G6 -> 1928.5545
A8: 7 | B8: =B7-F7 -> 10666.689 | C8: 0.24 | D8: =(B8*C8)/12 -> 213.33377 | E8: =D8*0.16 -> 34.133403 | F8: =G8-D8-E8 -> 1681.0873 | G8: =G7 -> 1928.5545
A9: 8 | B9: =B8-F8 -> 8985.6012 | C9: 0.24 | D9: =(B9*C9)/12 -> 179.71202 | E9: =D9*0.16 -> 28.753924 | F9: =G9-D9-E9 -> 1720.0886 | G9: =G8 -> 1928.5545
A10: 9 | B10: =B9-F9 -> 7265.5126 | C10: 0.24 | D10: =(B10*C10)/12 -> 145.31025 | E10: =D10*0.16 -> 23.24964 | F10: =G10-D10-E10 -> 1759.9946 | G10: =G9 -> 1928.5545
A11: 10 | B11: =B10-F10 -> 5505.518 | C11: 0.24 | D11: =(B11*C11)/12 -> 110.11036 | E11: =D11*0.16 -> 17.617658 | F11: =G11-D11-E11 -> 1800.8265 | G11: =G10 -> 1928.5545
A12: 11 | B12: =B11-F11 -> 3704.6915 | C12: 0.24 | D12: =(B12*C12)/12 -> 74.09383 | E12: =D12*0.16 -> 11.855013 | F12: =G12-D12-E12 -> 1842.6057 | G12: =G11 -> 1928.5545
A13: 12 | B13: =B12-F12 -> 1862.0858 | C13: 0.24 | D13: =(B13*C13)/12 -> 37.241717 | E13: =D13*0.16 -> 5.9586747 | F13: =G13-D13-E13 -> 1885.3541 | G13: =G12 -> 1928.5545
A14: 13 | B14: 20000 | C14: 0.24 | D14: =(B14*C14)/12 -> 400 | E14: =D14*0.16 -> 64 | F14: =G14-D14-E14 -> 1464.5545 | G14: =G13 -> 1928.5545
A15: 14 | B15: =B14-F14 -> 18535.445 | C15: 0.24 | D15: =(B15*C15)/12 -> 370.70891 | E15: =D15*0.16 -> 59.313426 | F15: =G15-D15-E15 -> 1498.5322 | G15: =G14 -> 1928.5545
A16: 15 | B16: =B15-F15 -> 17036.913 | C16: 0.24 | D16: =(B16*C16)/12 -> 340.73827 | E16: =D16*0.16 -> 54.518123 | F16: =G16-D16-E16 -> 1533.2981 | G16: =G15 -> 1928.5545
A17: 16 | B17: =B16-F16 -> 15503.615 | C17: 0.24 | D17: =(B17*C17)/12 -> 310.0723 | E17: =D17*0.16 -> 49.611569 | F17: =G17-D17-E17 -> 1568.8706 | G17: =G16 -> 1928.5545
A18: 17 | B18: =B17-F17 -> 13934.745 | C18: 0.24 | D18: =(B18*C18)/12 -> 278.69489 | E18: =D18*0.16 -> 44.591183 | F18: =G18-D18-E18 -> 1605.2684 | G18: =G17 -> 1928.5545
A19: 18 | B19: =B18-F18 -> 12329.476 | C19: 0.24 | D19: =(B19*C19)/12 -> 246.58952 | E19: =D19*0.16 -> 39.454323 | F19: =G19-D19-E19 -> 1642.5107 | G19: =G18 -> 1928.5545
A20: 19 | B20: =B19-F19 -> 10686.965 | C20: 0.24 | D20: =(B20*C20)/12 -> 213.73931 | E20: =D20*0.16 -> 34.198289 | F20: =G20-D20-E20 -> 1680.6169 | G20: =G19 -> 1928.5545
A21: 20 | B21: =B20-F20 -> 9006.3485 | C21: 0.24 | D21: =(B21*C21)/12 -> 180.12697 | E21: =D21*0.16 -> 28.820315 | F21: =G21-D21-E21 -> 1719.6072 | G21: =G20 -> 1928.5545
A22: 21 | B22: =B21-F21 -> 7286.7413 | C22: 0.24 | D22: =(B22*C22)/12 -> 145.73483 | E22: =D22*0.16 -> 23.317572 | F22: =G22-D22-E22 -> 1759.5021 | G22: =G21 -> 1928.5545
A23: 22 | B23: =B22-F22 -> 5527.2392 | C23: 0.24 | D23: =(B23*C23)/12 -> 110.54478 | E23: =D23*0.16 -> 17.687165 | F23: =G23-D23-E23 -> 1800.3226 | G23: =G22 -> 1928.5545
A24: 23 | B24: =B23-F23 -> 3726.9166 | C24: 0.24 | D24: =(B24*C24)/12 -> 74.538332 | E24: =D24*0.16 -> 11.926133 | F24: =G24-D24-E24 -> 1842.0901 | G24: =G23 -> 1928.5545
A25: 24 | B25: =B24-F24 -> 1884.8265 | C25: 0.24 | D25: =(B25*C25)/12 -> 37.696531 | E25: =D25*0.16 -> 6.0314449 | F25: =G25-D25-E25 -> 1884.8265 | G25: =G24 -> 1928.5545

Sheet PLACAS
A1: No. de Pago | B1: Saldo Capital | C1: Tasa Interés | D1: Pago Intereses | E1: IVA | F1: Pago Capital | G1: PAGO MENSUAL
A2: 1 | B2: 6350 | C2: 0.24 | D2: =(B2*C2)/12 -> 127 | E2: =D2*0.16 -> 20.32 | F2: =G2-D2-E2 -> 200.70445 | G2: =PMT((C2*1.16/12),24,-B2,0,0) -> 348.02445
A3: 2 | B3: =B2-F2 -> 6149.2956 | C3: 0.24 | D3: =(B3*C3)/12 -> 122.98591 | E3: =D3*0.16 -> 19.677746 | F3: =G3-D3-E3 -> 205.36079 | G3: =G2 -> 348.02445
A4: 3 | B4: =B3-F3 -> 5943.9348 | C4: 0.24 | D4: =(B4*C4)/12 -> 118.8787 | E4: =D4*0.16 -> 19.020591 | F4: =G4-D4-E4 -> 210.12516 | G4: =G3 -> 348.02445
A5: 4 | B5: =B4-F4 -> 5733.8096 | C5: 0.24 | D5: =(B5*C5)/12 -> 114.67619 | E5: =D5*0.16 -> 18.348191 | F5: =G5-D5-E5 -> 215.00007 | G5: =G4 -> 348.02445
A6: 5 | B6: =B5-F5 -> 5518.8095 | C6: 0.24 | D6: =(B6*C6)/12 -> 110.37619 | E6: =D6*0.16 -> 17.66019 | F6: =G6-D6-E6 -> 219.98807 | G6: =G5 -> 348.02445
A7: 6 | B7: =B6-F6 -> 5298.8215 | C7: 0.24 | D7: =(B7*C7)/12 -> 105.97643 | E7: =D7*0.16 -> 16.956229 | F7: =G7-D7-E7 -> 225.09179 | G7: =G6 -> 348.02445
A8: 7 | B8: =B7-F7 -> 5073.7297 | C8: 0.24 | D8: =(B8*C8)/12 -> 101.47459 | E8: =D8*0.16 -> 16.235935 | F8: =G8-D8-E8 -> 230.31392 | G8: =G7 -> 348.02445
A9: 8 | B9: =B8-F8 -> 4843.4158 | C9: 0.24 | D9: =(B9*C9)/12 -> 96.868315 | E9: =D9*0.16 -> 15.49893 | F9: =G9-D9-E9 -> 235.6572 | G9: =G8 -> 348.02445
A10: 9 | B10: =B9-F9 -> 4607.7585 | C10: 0.24 | D10: =(B10*C10)/12 -> 92.155171 | E10: =D10*0.16 -> 14.744827 | F10: =G10-D10-E10 -> 241.12445 | G10: =G9 -> 348.02445
A11: 10 | B11: =B10-F10 -> 4366.6341 | C11: 0.24 | D11: =(B11*C11)/12 -> 87.332682 | E11: =D11*0.16 -> 13.973229 | F11: =G11-D11-E11 -> 246.71854 | G11: =G10 -> 348.02445
A12: 11 | B12: =B11-F11 -> 4119.9156 | C12: 0.24 | D12: =(B12*C12)/12 -> 82.398311 | E12: =D12*0.16 -> 13.18373 | F12: =G12-D12-E12 -> 252.44241 | G12: =G11 -> 348.02445
A13: 12 | B13: =B12-F12 -> 3867.4732 | C13: 0.24 | D13: =(B13*C13)/12 -> 77.349463 | E13: =D13*0.16 -> 12.375914 | F13: =G13-D13-E13 -> 258.29907 | G13: =G12 -> 348.02445
A14: 13 | B14: =B13-F13 -> 3609.1741 | C14: 0.24 | D14: =(B14*C14)/12 -> 72.183482 | E14: =D14*0.16 -> 11.549357 | F14: =G14-D14-E14 -> 264.29161 | G14: =G13 -> 348.02445
... A25: 24 | B25: =B24-F24 -> 340.13335 | C25: 0.24 | D25: =(B25*C25)/12 -> 6.8026671 | E25: =D25*0.16 -> 1.0884267 | F25: =G25-D25-E25 -> 340.13335 | G25: =G24 -> 348.02445

Sheet GASTOS DE ARRENDAMIENTO
A1: No. de Pago | B1: Saldo Capital | C1: Tasa Interés | D1: Pago Intereses | E1: IVA | F1: Pago Capital | G1: PAGO MENSUAL
A2: 1 | B2: 8000 | C2: 0.24 | D2: =(B2*C2)/12 -> 160 | E2: =D2*0.16 -> 25.6 | F2: =G2-D2-E2 -> 252.856 | G2: =PMT((C2*1.16/12),24,-B2,0,0) -> 438.456
A3: 2 | B3: =B2-F2 -> 7747.144 | C3: 0.24 | D3: =(B3*C3)/12 -> 154.94288 | E3: =D3*0.16 -> 24.790861 | F3: =G3-D3-E3 -> 258.72226 | G3: =G2 -> 438.456
A4: 3 | B4: =B3-F3 -> 7488.4217 | C4: 0.24 | D4: =(B4*C4)/12 -> 149.76843 | E4: =D4*0.16 -> 23.96295 | F4: =G4-D4-E4 -> 264.72461 | G4: =G3 -> 438.456
A5: 4 | B5: =B4-F4 -> 7223.6971 | C5: 0.24 | D5: =(B5*C5)/12 -> 144.47394 | E5: =D5*0.16 -> 23.115831 | F5: =G5-D5-E5 -> 270.86622 | G5: =G4 -> 438.456
A6: 5 | B6: =B5-F5 -> 6952.8309 | C6: 0.24 | D6: =(B6*C6)/12 -> 139.05662 | E6: =D6*0.16 -> 22.249059 | F6: =G6-D6-E6 -> 277.15032 | G6: =G5 -> 438.456
A7: 6 | B7: =B6-F6 -> 6675.6806 | C7: 0.24 | D7: =(B7*C7)/12 -> 133.51361 | E7: =D7*0.16 -> 21.362178 | F7: =G7-D7-E7 -> 283.58021 | G7: =G6 -> 438.456
A8: 7 | B8: =B7-F7 -> 6392.1004 | C8: 0.24 | D8: =(B8*C8)/12 -> 127.84201 | E8: =D8*0.16 -> 20.454721 | F8: =G8-D8-E8 -> 290.15927 | G8: =G7 -> 438.456
A9: 8 | B9: =B8-F8 -> 6101.9411 | C9: 0.24 | D9: =(B9*C9)/12 -> 122.03882 | E9: =D9*0.16 -> 19.526212 | F9: =G9-D9-E9 -> 296.89096 | G9: =G8 -> 438.456
A10: 9 | B10: =B9-F9 -> 5805.0501 | C10: 0.24 | D10: =(B10*C10)/12 -> 116.101 | E10: =D10*0.16 -> 18.57616 | F10: =G10-D10-E10 -> 303.77884 | G10: =G9 -> 438.456
A11: 10 | B11: =B10-F10 -> 5501.2713 | C11: 0.24 | D11: =(B11*C11)/12 -> 110.02543 | E11: =D11*0.16 -> 17.604068 | F11: =G11-D11-E11 -> 310.8265 | G11: =G10 -> 438.456
A12: 11 | B12: =B11-F11 -> 5190.4448 | C12: 0.24 | D12: =(B12*C12)/12 -> 103.8089 | E12: =D12*0.16 -> 16.609423 | F12: =G12-D12-E12 -> 318.03768 | G12: =G11 -> 438.456
A13: 12 | B13: =B12-F12 -> 4872.4071 | C13: 0.24 | D13: =(B13*C13)/12 -> 97.448142 | E13: =D13*0.16 -> 15.591703 | F13: =G13-D13-E13 -> 325.41615 | G13: =G12 -> 438.456
A14: 13 | B14: =B13-F13 -> 4546.991 | C14: 0.24 | D14: =(B14*C14)/12 -> 90.939819 | E14: =D14*0.16 -> 14.550371 | F14: =G14-D14-E14 -> 332.96581 | G14: =G13 -> 438.456
... A25: 24 | B25: =B24-F24 -> 428.51446 | C25: 0.24 | D25: =(B25*C25)/12 -> 8.5702893 | E25: =D25*0.16 -> 1.3712463 | F25: =G25-D25-E25 -> 428.51446 | G25: =G24 -> 438.456

Sheet INTEGRAL
A1: No. de Pago | B1: Saldo Capital | C1: Tasa Interés | D1: Pago Intereses | E1: IVA FINANCIAMIENTOS | F1: Pago Capital | G1: Subtotal | I1: IVA ARRENDAMIENTO | K1: Pago Total | L1: RENTA CON IVA | M1: KILOMETRAJE CON IVA
A2: 1 | B2: =ARRENDAMIENTO!B2+SEGURO!B2+PLACAS!B2+'GASTOS DE ARRENDAMIENTO'!B2 -> 1174159.9 | C2: 24,00% | D2: =ARRENDAMIENTO!D2+SEGURO!D2+PLACAS!D2+'GASTOS DE ARRENDAMIENTO'!D2 -> 23483.199 | E2: =SEGURO!E2+PLACAS!E2+'GASTOS DE ARRENDAMIENTO'!E2 -> 91.84 | F2: =ARRENDAMIENTO!E2+SEGURO!F2+PLACAS!F2+'GASTOS DE ARRENDAMIENTO'!F2 -> 20192.376 | G2: =K2/1.16 -> 43392.935 | H2: =+D2+E2+F2 -> 43767.415 | I2: 1920 | J2: =+H2+I2 -> 45687.415 | K2: =ARRENDAMIENTO!H2+SEGURO!G2+PLACAS!G2+'GASTOS DE ARRENDAMIENTO'!G2 -> 50335.805 | L2: =K2-M2 -> 30499.805 | M2: 19836
A3: 2 | B3: =ARRENDAMIENTO!B3+SEGURO!B3+PLACAS!B3+'GASTOS DE ARRENDAMIENTO'!B3 -> 1153967.6 | C3: 24,00% | D3: =ARRENDAMIENTO!D3+SEGURO!D3+PLACAS!D3+'GASTOS DE ARRENDAMIENTO'!D3 -> 23079.351 | E3: =SEGURO!E3+PLACAS!E3+'GASTOS DE ARRENDAMIENTO'!E3 -> 103.72418 | F3: =ARRENDAMIENTO!E3+SEGURO!F3+PLACAS!F3+'GASTOS DE ARRENDAMIENTO'!F3 -> 20584.34 | G3: =K3/1.16 -> 43392.935 | I3: 1920 | K3: =ARRENDAMIENTO!H3+SEGURO!G3+PLACAS!G3+'GASTOS DE ARRENDAMIENTO'!G3 -> 50335.805 | L3: =K3-M3 -> 30499.805 | M3: 19836
A4: 3 | B4: =ARRENDAMIENTO!B4+SEGURO!B4+PLACAS!B4+'GASTOS DE ARRENDAMIENTO'!B4 -> 1133383.2 | C4: 24,00% | D4: =ARRENDAMIENTO!D4+SEGURO!D4+PLACAS!D4+'GASTOS DE ARRENDAMIENTO'!D4 -> 22667.664 | E4: =SEGURO!E4+PLACAS!E4+'GASTOS DE ARRENDAMIENTO'!E4 -> 97.442465 | F4: =ARRENDAMIENTO!E4+SEGURO!F4+PLACAS!F4+'GASTOS DE ARRENDAMIENTO'!F4 -> 21002.308 | G4: =K4/1.16 -> 43392.935 | I4: 1920 | K4: =ARRENDAMIENTO!H4+SEGURO!G4+PLACAS!G4+'GASTOS DE ARRENDAMIENTO'!G4 -> 50335.805 | L4: =K4-M4 -> 30499.805 | M4: 19836
A5: 4 | B5: =ARRENDAMIENTO!B5+SEGURO!B5+PLACAS!B5+'GASTOS DE ARRENDAMIENTO'!B5 -> 1112380.9 | C5: 24,00% | D5: =ARRENDAMIENTO!D5+SEGURO!D5+PLACAS!D5+'GASTOS DE ARRENDAMIENTO'!D5 -> 22247.618 | E5: =SEGURO!E5+PLACAS!E5+'GASTOS DE ARRENDAMIENTO'!E5 -> 91.015018 | F5: =ARRENDAMIENTO!E5+SEGURO!F5+PLACAS!F5+'GASTOS DE ARRENDAMIENTO'!F5 -> 21428.782 | G5: =K5/1.16 -> 43392.935 | I5: 1920 | K5: =ARRENDAMIENTO!H5+SEGURO!G5+PLACAS!G5+'GASTOS DE ARRENDAMIENTO'!G5 -> 50335.805 | L5: =K5-M5 -> 30499.805 | M5: 19836
A6: 5 | B6: =ARRENDAMIENTO!B6+SEGURO!B6+PLACAS!B6+'GASTOS DE ARRENDAMIENTO'!B6 -> 1090952.1 | C6: 24,00% | D6: =ARRENDAMIENTO!D6+SEGURO!D6+PLACAS!D6+'GASTOS DE ARRENDAMIENTO'!D6 -> 21819.042 | E6: =SEGURO!E6+PLACAS!E6+'GASTOS DE ARRENDAMIENTO'!E6 -> 84.438455 | F6: =ARRENDAMIENTO!E6+SEGURO!F6+PLACAS!F6+'GASTOS DE ARRENDAMIENTO'!F6 -> 21863.934 | G6: =K6/1.16 -> 43392.935 | I6: 1920 | K6: =ARRENDAMIENTO!H6+SEGURO!G6+PLACAS!G6+'GASTOS DE ARRENDAMIENTO'!G6 -> 50335.805 | L6: =K6-M6 -> 30499.805 | M6: 19836
A7: 6 | B7: =ARRENDAMIENTO!B7+SEGURO!B7+PLACAS!B7+'GASTOS DE ARRENDAMIENTO'!B7 -> 1069088.2 | C7: 24,00% | D7: =ARRENDAMIENTO!D7+SEGURO!D7+PLACAS!D7+'GASTOS DE ARRENDAMIENTO'!D7 -> 21381.764 | E7: =SEGURO!E7+PLACAS!E7+'GASTOS DE ARRENDAMIENTO'!E7 -> 77.709315 | F7: =ARRENDAMIENTO!E7+SEGURO!F7+PLACAS!F7+'GASTOS DE ARRENDAMIENTO'!F7 -> 22307.942 | G7: =K7/1.16 -> 43392.935 | I7: 1920 | K7: =ARRENDAMIENTO!H7+SEGURO!G7+PLACAS!G7+'GASTOS DE ARRENDAMIENTO'!G7 -> 50335.805 | L7: =K7-M7 -> 30499.805 | M7: 19836
A8: 7 | B8: =ARRENDAMIENTO!B8+SEGURO!B8+PLACAS!B8+'GASTOS DE ARRENDAMIENTO'!B8 -> 1046780.2 | C8: 24,00% | D8: =ARRENDAMIENTO!D8+SEGURO!D8+PLACAS!D8+'GASTOS DE ARRENDAMIENTO'!D8 -> 20935.605 | E8: =SEGURO!E8+PLACAS!E8+'GASTOS DE ARRENDAMIENTO'!E8 -> 70.824059 | F8: =ARRENDAMIENTO!E8+SEGURO!F8+PLACAS!F8+'GASTOS DE ARRENDAMIENTO'!F8 -> 22760.986 | G8: =K8/1.16 -> 43392.935 | I8: 1920 | K8: =ARRENDAMIENTO!H8+SEGURO!G8+PLACAS!G8+'GASTOS DE ARRENDAMIENTO'!G8 -> 50335.805 | L8: =K8-M8 -> 30499.805 | M8: 19836
A9: 8 | B9: =ARRENDAMIENTO!B9+SEGURO!B9+PLACAS!B9+'GASTOS DE ARRENDAMIENTO'!B9 -> 1024019.3 | C9: 24,00% | D9: =ARRENDAMIENTO!D9+SEGURO!D9+PLACAS!D9+'GASTOS DE ARRENDAMIENTO'!D9 -> 20480.385 | E9: =SEGURO!E9+PLACAS!E9+'GASTOS DE ARRENDAMIENTO'!E9 -> 63.779066 | F9: =ARRENDAMIENTO!E9+SEGURO!F9+PLACAS!F9+'GASTOS DE ARRENDAMIENTO'!F9 -> 23223.251 | G9: =K9/1.16 -> 43392.935 | I9: 1920 | K9: =ARRENDAMIENTO!H9+SEGURO!G9+PLACAS!G9+'GASTOS DE ARRENDAMIENTO'!G9 -> 50335.805 | L9: =K9-M9 -> 30499.805 | M9: 19836
A10: 9 | B10: =ARRENDAMIENTO!B10+SEGURO!B10+PLACAS!B10+'GASTOS DE ARRENDAMIENTO'!B10 -> 1000796 | C10: 24,00% | D10: =ARRENDAMIENTO!D10+SEGURO!D10+PLACAS!D10+'GASTOS DE ARRENDAMIENTO'!D10 -> 20015.92 | E10: =SEGURO!E10+PLACAS!E10+'GASTOS DE ARRENDAMIENTO'!E10 -> 56.570628 | F10: =ARRENDAMIENTO!E10+SEGURO!F10+PLACAS!F10+'GASTOS DE ARRENDAMIENTO'!F10 -> 23694.924 | G10: =K10/1.16 -> 43392.935 | I10: 1920 | K10: =ARRENDAMIENTO!H10+SEGURO!G10+PLACAS!G10+'GASTOS DE ARRENDAMIENTO'!G10 -> 50335.805 | L10: =K10-M10 -> 30499.805 | M10: 19836
A11: 10 | B11: =ARRENDAMIENTO!B11+SEGURO!B11+PLACAS!B11+'GASTOS DE ARRENDAMIENTO'!B11 -> 977101.09 | C11: 24,00% | D11: =ARRENDAMIENTO!D11+SEGURO!D11+PLACAS!D11+'GASTOS DE ARRENDAMIENTO'!D11 -> 19542.022 | E11: =SEGURO!E11+PLACAS!E11+'GASTOS DE ARRENDAMIENTO'!E11 -> 49.194955 | F11: =ARRENDAMIENTO!E11+SEGURO!F11+PLACAS!F11+'GASTOS DE ARRENDAMIENTO'!F11 -> 24176.198 | G11: =K11/1.16 -> 43392.935 | I11: 1920 | K11: =ARRENDAMIENTO!H11+SEGURO!G11+PLACAS!G11+'GASTOS DE ARRENDAMIENTO'!G11 -> 50335.805 | L11: =K11-M11 -> 30499.805 | M11: 19836
A12: 11 | B12: =ARRENDAMIENTO!B12+SEGURO!B12+PLACAS!B12+'GASTOS DE ARRENDAMIENTO'!B12 -> 952924.89 | C12: 24,00% | D12: =ARRENDAMIENTO!D12+SEGURO!D12+PLACAS!D12+'GASTOS DE ARRENDAMIENTO'!D12 -> 19058.498 | E12: =SEGURO!E12+PLACAS!E12+'GASTOS DE ARRENDAMIENTO'!E12 -> 41.648166 | F12: =ARRENDAMIENTO!E12+SEGURO!F12+PLACAS!F12+'GASTOS DE ARRENDAMIENTO'!F12 -> 24667.269 | G12: =K12/1.16 -> 43392.935 | I12: 1920 | K12: =ARRENDAMIENTO!H12+SEGURO!G12+PLACAS!G12+'GASTOS DE ARRENDAMIENTO'!G12 -> 50335.805 | L12: =K12-M12 -> 30499.805 | M12: 19836
A13: 12 | B13: =ARRENDAMIENTO!B13+SEGURO!B13+PLACAS!B13+'GASTOS DE ARRENDAMIENTO'!B13 -> 928257.62 | C13: 24,00% | D13: =ARRENDAMIENTO!D13+SEGURO!D13+PLACAS!D13+'GASTOS DE ARRENDAMIENTO'!D13 -> 18565.152 | E13: =SEGURO!E13+PLACAS!E13+'GASTOS DE ARRENDAMIENTO'!E13 -> 33.926292 | F13: =ARRENDAMIENTO!E13+SEGURO!F13+PLACAS!F13+'GASTOS DE ARRENDAMIENTO'!F13 -> 25168.336 | G13: =K13/1.16 -> 43392.935 | I13: 1920 | K13: =ARRENDAMIENTO!H13+SEGURO!G13+PLACAS!G13+'GASTOS DE ARRENDAMIENTO'!G13 -> 50335.805 | L13: =K13-M13 -> 30499.805 | M13: 19836
A14: 13 | B14: =ARRENDAMIENTO!B14+SEGURO!B14+PLACAS!B14+'GASTOS DE ARRENDAMIENTO'!B14 -> 923112.55 | C14: 24,00% | D14: =ARRENDAMIENTO!D14+SEGURO!D14+PLACAS!D14+'GASTOS DE ARRENDAMIENTO'!D14 -> 18462.251 | E14: =SEGURO!E14+PLACAS!E14+'GASTOS DE ARRENDAMIENTO'!E14 -> 90.099728 | F14: =ARRENDAMIENTO!E14+SEGURO!F14+PLACAS!F14+'GASTOS DE ARRENDAMIENTO'!F14 -> 25215.064 | G14: =K14/1.16 -> 43392.935 | I14: 1920 | K14: =ARRENDAMIENTO!H14+SEGURO!G14+PLACAS!G14+'GASTOS DE ARRENDAMIENTO'!G14 -> 50335.805 | L14: =K14-M14 -> 30499.805 | M14: 19836
... A25: 24 | B25: =ARRENDAMIENTO!B25+SEGURO!B25+PLACAS!B25+'GASTOS DE ARRENDAMIENTO'!B25 -> 615864.52 | C25: 24,00% | D25: =ARRENDAMIENTO!D25+SEGURO!D25+PLACAS!D25+'GASTOS DE ARRENDAMIENTO'!D25 -> 12317.29 | E25: =SEGURO!E25+PLACAS!E25+'GASTOS DE ARRENDAMIENTO'!E25 -> 8.4911179 | F25: =ARRENDAMIENTO!E25+SEGURO!F25+PLACAS!F25+'GASTOS DE ARRENDAMIENTO'!F25 -> 31441.633 | G25: =K25/1.16 -> 43392.935 | I25: 1920 | K25: =ARRENDAMIENTO!H25+SEGURO!G25+PLACAS!G25+'GASTOS DE ARRENDAMIENTO'!G25 -> 50335.805 | L25: =K25-M25 -> 30499.805 | M25: 19836
B29: sol_condiciones_art
